voyager.cp38-win_amd64.pyd
voyager-2.1.0.dist-info/METADATA
voyager-2.1.0.dist-info/WHEEL
voyager-2.1.0.dist-info/top_level.txt
voyager-2.1.0.dist-info/RECORD
